django_allauth_webauthn/__init__.py
django_allauth_webauthn/adapter.py
django_allauth_webauthn/admin.py
django_allauth_webauthn/app_settings.py
django_allauth_webauthn/migrations/0001_initial.py
django_allauth_webauthn/migrations/__init__.py
django_allauth_webauthn/models.py
django_allauth_webauthn/templates/django_allauth_webauthn/login-script.html
django_allauth_webauthn/templates/django_allauth_webauthn/login.html
django_allauth_webauthn/templates/django_allauth_webauthn/register-script.html
django_allauth_webauthn/urls.py
django_allauth_webauthn/utils.py
django_allauth_webauthn/views.py
django_allauth_webauthn-0.2.3.dist-info/LICENSE
django_allauth_webauthn-0.2.3.dist-info/METADATA
django_allauth_webauthn-0.2.3.dist-info/WHEEL
django_allauth_webauthn-0.2.3.dist-info/RECORD
