Metadata-Version: 2.1
Name: django-allauth-webauthn
Version: 0.2.3
Summary: Webauthn-based two-factor authentication for Django allauth
Home-page: https://github.com/cyberdeck/django-allauth-webauthn
License: MIT
Author: H. Gregor Molter
Author-email: gregor.molter@secretlab.de
Requires-Python: >=3.10,<4.0
Classifier: Development Status :: 3 - Alpha
Classifier: Intended Audience :: Developers
Classifier: License :: OSI Approved :: MIT License
Classifier: Programming Language :: Python :: 3
Classifier: Programming Language :: Python :: 3.10
Classifier: Programming Language :: Python :: 3.11
Classifier: Programming Language :: Python :: 3.12
Classifier: Programming Language :: Python :: 3 :: Only
Classifier: Topic :: Software Development :: Libraries :: Python Modules
Requires-Dist: Django (>=4.2.8,<5.0.0)
Requires-Dist: django-allauth (>=0.45.0,<0.46.0)
Requires-Dist: webauthn (>=0.4.7,<0.5.0)
Project-URL: Bug Tracker, https://github.com/cyberdeck/django-allauth-webauthn/issues
Project-URL: Documentation, https://django-allauth-webauthn.readthedocs.io/en/latest/
Project-URL: Repository, https://github.com/cyberdeck/django-allauth-webauthn
